a2a_alert_agent/__init__.py
a2a_alert_agent/__main__.py
a2a_alert_agent/agent.py
a2a_alert_agent/agent_executor.py
a2a_alert_agent/mcp_servers.py
a2a_alert_agent/setting.py
a2a_alert_agent/test_client.py
a2a_alert_agent/zmp_mcp_client_manager.py
a2a_alert_agent-0.1.1.dist-info/METADATA
a2a_alert_agent-0.1.1.dist-info/WHEEL
a2a_alert_agent-0.1.1.dist-info/entry_points.txt
a2a_alert_agent-0.1.1.dist-info/RECORD
